{
"meta":{"test_sets":[],"test_metrics":[],"learn_metrics":[{"best_value":"Min","name":"RMSE"}],"launch_mode":"Train","parameters":"","iteration_count":100,"learn_sets":["learn"],"name":"experiment"},
"iterations":[
{"learn":[8.728197315],"iteration":0,"passed_time":0.005745756789,"remaining_time":0.5688299221},
{"learn":[8.251551712],"iteration":1,"passed_time":0.01208956622,"remaining_time":0.5923887448},
{"learn":[7.769877986],"iteration":2,"passed_time":0.01750491017,"remaining_time":0.5659920956},
{"learn":[7.37049254],"iteration":3,"passed_time":0.02252993464,"remaining_time":0.5407184314},
{"learn":[7.01668514],"iteration":4,"passed_time":0.02985612862,"remaining_time":0.5672664438},
{"learn":[6.697169389],"iteration":5,"passed_time":0.03535278846,"remaining_time":0.5538603525},
{"learn":[6.419492286],"iteration":6,"passed_time":0.04006752397,"remaining_time":0.5323256756},
{"learn":[6.130399556],"iteration":7,"passed_time":0.04667446324,"remaining_time":0.5367563272},
{"learn":[5.857082739],"iteration":8,"passed_time":0.0517426957,"remaining_time":0.5231761454},
{"learn":[5.591376462],"iteration":9,"passed_time":0.05672655738,"remaining_time":0.5105390165},
{"learn":[5.323532389],"iteration":10,"passed_time":0.06439324178,"remaining_time":0.5209998653},
{"learn":[5.134178258],"iteration":11,"passed_time":0.06960606194,"remaining_time":0.5104444542},
{"learn":[4.919081132],"iteration":12,"passed_time":0.0768861753,"remaining_time":0.5145459424},
{"learn":[4.712666354],"iteration":13,"passed_time":0.08220833122,"remaining_time":0.5049940347},
{"learn":[4.545563217],"iteration":14,"passed_time":0.08752208318,"remaining_time":0.4959584714},
{"learn":[4.369113414],"iteration":15,"passed_time":0.09499485002,"remaining_time":0.4987229626},
{"learn":[4.215107081],"iteration":16,"passed_time":0.1004748921,"remaining_time":0.490553885},
{"learn":[4.091683095],"iteration":17,"passed_time":0.10669177,"remaining_time":0.4860402857},
{"learn":[3.987469938],"iteration":18,"passed_time":0.1111980326,"remaining_time":0.4740547704},
{"learn":[3.843121314],"iteration":19,"passed_time":0.1156358339,"remaining_time":0.4625433356},
{"learn":[3.721764394],"iteration":20,"passed_time":0.1216339244,"remaining_time":0.4575752393},
{"learn":[3.634335266],"iteration":21,"passed_time":0.1266902284,"remaining_time":0.4491744461},
{"learn":[3.565165979],"iteration":22,"passed_time":0.13112203,"remaining_time":0.4389737528},
{"learn":[3.475250976],"iteration":23,"passed_time":0.1376175416,"remaining_time":0.4357888818},
{"learn":[3.404050157],"iteration":24,"passed_time":0.1428431769,"remaining_time":0.4285295306},
{"learn":[3.336886896],"iteration":25,"passed_time":0.1472016538,"remaining_time":0.418958553},
{"learn":[3.280191844],"iteration":26,"passed_time":0.1534977094,"remaining_time":0.4150123253},
{"learn":[3.239286258],"iteration":27,"passed_time":0.157443867,"remaining_time":0.4048556579},
{"learn":[3.206912709],"iteration":28,"passed_time":0.1618767538,"remaining_time":0.396318949},
{"learn":[3.14305516],"iteration":29,"passed_time":0.1668332687,"remaining_time":0.3892776271},
{"learn":[3.091806269],"iteration":30,"passed_time":0.1735422329,"remaining_time":0.3862714216},
{"learn":[3.022211593],"iteration":31,"passed_time":0.1781270533,"remaining_time":0.3785199884},
{"learn":[2.98831319],"iteration":32,"passed_time":0.1828480871,"remaining_time":0.3712370254},
{"learn":[2.944631096],"iteration":33,"passed_time":0.189194763,"remaining_time":0.3672604222},
{"learn":[2.904820305],"iteration":34,"passed_time":0.1937118671,"remaining_time":0.3597506103},
{"learn":[2.872516533],"iteration":35,"passed_time":0.1985660764,"remaining_time":0.3530063581},
{"learn":[2.8521569],"iteration":36,"passed_time":0.2015652374,"remaining_time":0.3432056745},
{"learn":[2.805979301],"iteration":37,"passed_time":0.2070623072,"remaining_time":0.3378385012},
{"learn":[2.759229212],"iteration":38,"passed_time":0.2116772094,"remaining_time":0.331084866},
{"learn":[2.721534293],"iteration":39,"passed_time":0.2185202024,"remaining_time":0.3277803036},
{"learn":[2.678878726],"iteration":40,"passed_time":0.2235476066,"remaining_time":0.3216904582},
{"learn":[2.656138262],"iteration":41,"passed_time":0.2282082666,"remaining_time":0.3151447492},
{"learn":[2.62718904],"iteration":42,"passed_time":0.2345990538,"remaining_time":0.310980141},
{"learn":[2.590616929],"iteration":43,"passed_time":0.2394609364,"remaining_time":0.3047684645},
{"learn":[2.559161988],"iteration":44,"passed_time":0.2442813372,"remaining_time":0.2985660789},
{"learn":[2.54593484],"iteration":45,"passed_time":0.2509315091,"remaining_time":0.2945717716},
{"learn":[2.524042942],"iteration":46,"passed_time":0.2557549018,"remaining_time":0.2884044638},
{"learn":[2.498873878],"iteration":47,"passed_time":0.2605359682,"remaining_time":0.2822472989},
{"learn":[2.473327254],"iteration":48,"passed_time":0.2676362495,"remaining_time":0.278560178},
{"learn":[2.447842124],"iteration":49,"passed_time":0.2720585908,"remaining_time":0.2720585908},
{"learn":[2.430444717],"iteration":50,"passed_time":0.2767431728,"remaining_time":0.2658904994},
{"learn":[2.409479631],"iteration":51,"passed_time":0.282984014,"remaining_time":0.2612160129},
{"learn":[2.390702518],"iteration":52,"passed_time":0.2877424025,"remaining_time":0.2551677909},
{"learn":[2.375280818],"iteration":53,"passed_time":0.292331966,"remaining_time":0.2490235266},
{"learn":[2.360007254],"iteration":54,"passed_time":0.3000885955,"remaining_time":0.2455270327},
{"learn":[2.352287942],"iteration":55,"passed_time":0.3048013283,"remaining_time":0.239486758},
{"learn":[2.328252344],"iteration":56,"passed_time":0.3093655036,"remaining_time":0.2333809939},
{"learn":[2.323862544],"iteration":57,"passed_time":0.3154515243,"remaining_time":0.2284304142},
{"learn":[2.307159496],"iteration":58,"passed_time":0.3202249203,"remaining_time":0.2225291819},
{"learn":[2.299442683],"iteration":59,"passed_time":0.3248791028,"remaining_time":0.2165860685},
{"learn":[2.286932392],"iteration":60,"passed_time":0.3322656309,"remaining_time":0.2124321247},
{"learn":[2.263853506],"iteration":61,"passed_time":0.3371386621,"remaining_time":0.2066333736},
{"learn":[2.248711609],"iteration":62,"passed_time":0.3421429801,"remaining_time":0.2009411153},
{"learn":[2.229474487],"iteration":63,"passed_time":0.3490188633,"remaining_time":0.1963231106},
{"learn":[2.218122557],"iteration":64,"passed_time":0.3538853297,"remaining_time":0.1905536391},
{"learn":[2.204973867],"iteration":65,"passed_time":0.3600306849,"remaining_time":0.1854703528},
{"learn":[2.188885043],"iteration":66,"passed_time":0.3652118418,"remaining_time":0.1798804594},
{"learn":[2.169770673],"iteration":67,"passed_time":0.3696666321,"remaining_time":0.1739607681},
{"learn":[2.159751218],"iteration":68,"passed_time":0.3748336644,"remaining_time":0.1684035304},
{"learn":[2.156043342],"iteration":69,"passed_time":0.3796976594,"remaining_time":0.1627275683},
{"learn":[2.148508639],"iteration":70,"passed_time":0.3842686463,"remaining_time":0.1569547992},
{"learn":[2.13508276],"iteration":71,"passed_time":0.3891725926,"remaining_time":0.1513448971},
{"learn":[2.124734936],"iteration":72,"passed_time":0.3954142349,"remaining_time":0.1462491006},
{"learn":[2.111603448],"iteration":73,"passed_time":0.4000861044,"remaining_time":0.1405707935},
{"learn":[2.096220874],"iteration":74,"passed_time":0.4053845957,"remaining_time":0.1351281986},
{"learn":[2.083617092],"iteration":75,"passed_time":0.4103516633,"remaining_time":0.1295847358},
{"learn":[2.072266951],"iteration":76,"passed_time":0.4145350753,"remaining_time":0.1238221653},
{"learn":[2.058811392],"iteration":77,"passed_time":0.4191190308,"remaining_time":0.11821306},
{"learn":[2.055840481],"iteration":78,"passed_time":0.4257124576,"remaining_time":0.113164071},
{"learn":[2.039449513],"iteration":79,"passed_time":0.4289931687,"remaining_time":0.1072482922},
{"learn":[2.025932939],"iteration":80,"passed_time":0.4322669984,"remaining_time":0.1013959626},
{"learn":[2.013474221],"iteration":81,"passed_time":0.4367924936,"remaining_time":0.09588127907},
{"learn":[1.999299484],"iteration":82,"passed_time":0.4396387546,"remaining_time":0.09004649191},
{"learn":[1.98904578],"iteration":83,"passed_time":0.442260671,"remaining_time":0.08424012781},
{"learn":[1.985548212],"iteration":84,"passed_time":0.444798353,"remaining_time":0.078493827},
{"learn":[1.970344115],"iteration":85,"passed_time":0.4472165349,"remaining_time":0.07280269173},
{"learn":[1.960579817],"iteration":86,"passed_time":0.4497194542,"remaining_time":0.06719945867},
{"learn":[1.948928683],"iteration":87,"passed_time":0.4545607421,"remaining_time":0.06198555574},
{"learn":[1.935056287],"iteration":88,"passed_time":0.4572607915,"remaining_time":0.05651537872},
{"learn":[1.923825368],"iteration":89,"passed_time":0.4596970908,"remaining_time":0.05107745454},
{"learn":[1.910032402],"iteration":90,"passed_time":0.4622460636,"remaining_time":0.04571664365},
{"learn":[1.902423425],"iteration":91,"passed_time":0.4646801718,"remaining_time":0.04040697146},
{"learn":[1.892761427],"iteration":92,"passed_time":0.4692516608,"remaining_time":0.03532001748},
{"learn":[1.877477465],"iteration":93,"passed_time":0.4716888769,"remaining_time":0.03010780065},
{"learn":[1.872800711],"iteration":94,"passed_time":0.4740888271,"remaining_time":0.02495204353},
{"learn":[1.858240946],"iteration":95,"passed_time":0.4765848337,"remaining_time":0.01985770141},
{"learn":[1.853708539],"iteration":96,"passed_time":0.4789743677,"remaining_time":0.01481364024},
{"learn":[1.838265506],"iteration":97,"passed_time":0.4815144185,"remaining_time":0.009826824868},
{"learn":[1.832531895],"iteration":98,"passed_time":0.4864258842,"remaining_time":0.004913392769},
{"learn":[1.822340038],"iteration":99,"passed_time":0.4890418931,"remaining_time":0}
]}